[
  {
    "url": "https://api.github.com/repos/browserify/browserify/issues/comments/50552831",
    "html_url": "https://github.com/browserify/browserify/pull/844#issuecomment-50552831",
    "issue_url": "https://api.github.com/repos/browserify/browserify/issues/844",
    "id": 50552831,
    "node_id": "MDEyOklzc3VlQ29tbWVudDUwNTUyODMx",
    "user": {
      "login": "ghost",
      "id": 10137,
      "node_id": "MDQ6VXNlcjEwMTM3",
      "avatar_url": "https://avatars.githubusercontent.com/u/10137?v=4",
      "gravatar_id": "",
      "url": "https://api.github.com/users/ghost",
      "html_url": "https://github.com/ghost",
      "followers_url": "https://api.github.com/users/ghost/followers",
      "following_url": "https://api.github.com/users/ghost/following{/other_user}",
      "gists_url": "https://api.github.com/users/ghost/gists{/gist_id}",
      "starred_url": "https://api.github.com/users/ghost/starred{/owner}{/repo}",
      "subscriptions_url": "https://api.github.com/users/ghost/subscriptions",
      "organizations_url": "https://api.github.com/users/ghost/orgs",
      "repos_url": "https://api.github.com/users/ghost/repos",
      "events_url": "https://api.github.com/users/ghost/events{/privacy}",
      "received_events_url": "https://api.github.com/users/ghost/received_events",
      "type": "User",
      "site_admin": false
    },
    "created_at": "2014-07-29T23:18:36Z",
    "updated_at": "2014-07-29T23:18:36Z",
    "author_association": "NONE",
    "body": "Do you think there are many more of these sorts of issues that transforms will need to have? If so, it would make sense to pass in all the options as another parameter. If not, this seems reasonable. I just don't want to police the boundaries of which global options get passed in and which ones don't if people come along with other options they need passed in from the global constructor.\n",
    "reactions": {
      "url": "https://api.github.com/repos/browserify/browserify/issues/comments/50552831/reactions",
      "total_count": 0,
      "+1": 0,
      "-1": 0,
      "laugh": 0,
      "hooray": 0,
      "confused": 0,
      "heart": 0,
      "rocket": 0,
      "eyes": 0
    },
    "performed_via_github_app": null
  },
  {
    "url": "https://api.github.com/repos/browserify/browserify/issues/comments/50628474",
    "html_url": "https://github.com/browserify/browserify/pull/844#issuecomment-50628474",
    "issue_url": "https://api.github.com/repos/browserify/browserify/issues/844",
    "id": 50628474,
    "node_id": "MDEyOklzc3VlQ29tbWVudDUwNjI4NDc0",
    "user": {
      "login": "hughsk",
      "id": 569817,
      "node_id": "MDQ6VXNlcjU2OTgxNw==",
      "avatar_url": "https://avatars.githubusercontent.com/u/569817?v=4",
      "gravatar_id": "",
      "url": "https://api.github.com/users/hughsk",
      "html_url": "https://github.com/hughsk",
      "followers_url": "https://api.github.com/users/hughsk/followers",
      "following_url": "https://api.github.com/users/hughsk/following{/other_user}",
      "gists_url": "https://api.github.com/users/hughsk/gists{/gist_id}",
      "starred_url": "https://api.github.com/users/hughsk/starred{/owner}{/repo}",
      "subscriptions_url": "https://api.github.com/users/hughsk/subscriptions",
      "organizations_url": "https://api.github.com/users/hughsk/orgs",
      "repos_url": "https://api.github.com/users/hughsk/repos",
      "events_url": "https://api.github.com/users/hughsk/events{/privacy}",
      "received_events_url": "https://api.github.com/users/hughsk/received_events",
      "type": "User",
      "site_admin": false
    },
    "created_at": "2014-07-30T15:12:37Z",
    "updated_at": "2014-07-30T15:12:37Z",
    "author_association": "MEMBER",
    "body": "@substack actually, I think I like that idea more – other flags such as `entry`, `ignore-missing` and `standalone` might be useful for other cases. Let me know if you want me to adapt the pull request? :)\n",
    "reactions": {
      "url": "https://api.github.com/repos/browserify/browserify/issues/comments/50628474/reactions",
      "total_count": 0,
      "+1": 0,
      "-1": 0,
      "laugh": 0,
      "hooray": 0,
      "confused": 0,
      "heart": 0,
      "rocket": 0,
      "eyes": 0
    },
    "performed_via_github_app": null
  }
]