[
  {
    "url": "https://api.github.com/repos/expressjs/express/issues/comments/818789",
    "html_url": "https://github.com/expressjs/express/issues/538#issuecomment-818789",
    "issue_url": "https://api.github.com/repos/expressjs/express/issues/538",
    "id": 818789,
    "node_id": "MDEyOklzc3VlQ29tbWVudDgxODc4OQ==",
    "user": {
      "login": "tj",
      "id": 25254,
      "node_id": "MDQ6VXNlcjI1MjU0",
      "avatar_url": "https://avatars.githubusercontent.com/u/25254?v=4",
      "gravatar_id": "",
      "url": "https://api.github.com/users/tj",
      "html_url": "https://github.com/tj",
      "followers_url": "https://api.github.com/users/tj/followers",
      "following_url": "https://api.github.com/users/tj/following{/other_user}",
      "gists_url": "https://api.github.com/users/tj/gists{/gist_id}",
      "starred_url": "https://api.github.com/users/tj/starred{/owner}{/repo}",
      "subscriptions_url": "https://api.github.com/users/tj/subscriptions",
      "organizations_url": "https://api.github.com/users/tj/orgs",
      "repos_url": "https://api.github.com/users/tj/repos",
      "events_url": "https://api.github.com/users/tj/events{/privacy}",
      "received_events_url": "https://api.github.com/users/tj/received_events",
      "type": "User",
      "site_admin": false
    },
    "created_at": "2011-02-28T17:41:31Z",
    "updated_at": "2011-02-28T17:41:31Z",
    "author_association": "MEMBER",
    "body": "well `/:category` is all-consuming so say good-bye to `/login` or anything else unless they are defined _before_ this route. That being said, just add staticProvider above like this:\n\n```\n  app.use(connect.staticProvider(....))\n  app.use(app.router)\n  app.use(connect.errorHandler(or whatever else below)\n```\n",
    "reactions": {
      "url": "https://api.github.com/repos/expressjs/express/issues/comments/818789/reactions",
      "total_count": 0,
      "+1": 0,
      "-1": 0,
      "laugh": 0,
      "hooray": 0,
      "confused": 0,
      "heart": 0,
      "rocket": 0,
      "eyes": 0
    },
    "performed_via_github_app": null
  },
  {
    "url": "https://api.github.com/repos/expressjs/express/issues/comments/820649",
    "html_url": "https://github.com/expressjs/express/issues/538#issuecomment-820649",
    "issue_url": "https://api.github.com/repos/expressjs/express/issues/538",
    "id": 820649,
    "node_id": "MDEyOklzc3VlQ29tbWVudDgyMDY0OQ==",
    "user": {
      "login": "SiegfriedEhret",
      "id": 537567,
      "node_id": "MDQ6VXNlcjUzNzU2Nw==",
      "avatar_url": "https://avatars.githubusercontent.com/u/537567?v=4",
      "gravatar_id": "",
      "url": "https://api.github.com/users/SiegfriedEhret",
      "html_url": "https://github.com/SiegfriedEhret",
      "followers_url": "https://api.github.com/users/SiegfriedEhret/followers",
      "following_url": "https://api.github.com/users/SiegfriedEhret/following{/other_user}",
      "gists_url": "https://api.github.com/users/SiegfriedEhret/gists{/gist_id}",
      "starred_url": "https://api.github.com/users/SiegfriedEhret/starred{/owner}{/repo}",
      "subscriptions_url": "https://api.github.com/users/SiegfriedEhret/subscriptions",
      "organizations_url": "https://api.github.com/users/SiegfriedEhret/orgs",
      "repos_url": "https://api.github.com/users/SiegfriedEhret/repos",
      "events_url": "https://api.github.com/users/SiegfriedEhret/events{/privacy}",
      "received_events_url": "https://api.github.com/users/SiegfriedEhret/received_events",
      "type": "User",
      "site_admin": false
    },
    "created_at": "2011-03-01T01:32:09Z",
    "updated_at": "2011-03-01T01:32:09Z",
    "author_association": "NONE",
    "body": "I used the app.router before defining the staticProvider.\nThanks a lot !\n",
    "reactions": {
      "url": "https://api.github.com/repos/expressjs/express/issues/comments/820649/reactions",
      "total_count": 0,
      "+1": 0,
      "-1": 0,
      "laugh": 0,
      "hooray": 0,
      "confused": 0,
      "heart": 0,
      "rocket": 0,
      "eyes": 0
    },
    "performed_via_github_app": null
  }
]