[
  {
    "url": "https://api.github.com/repos/lodash/lodash/issues/comments/120939755",
    "html_url": "https://github.com/lodash/lodash/pull/1340#issuecomment-120939755",
    "issue_url": "https://api.github.com/repos/lodash/lodash/issues/1340",
    "id": 120939755,
    "node_id": "MDEyOklzc3VlQ29tbWVudDEyMDkzOTc1NQ==",
    "user": {
      "login": "jdalton",
      "id": 4303,
      "node_id": "MDQ6VXNlcjQzMDM=",
      "avatar_url": "https://avatars.githubusercontent.com/u/4303?v=4",
      "gravatar_id": "",
      "url": "https://api.github.com/users/jdalton",
      "html_url": "https://github.com/jdalton",
      "followers_url": "https://api.github.com/users/jdalton/followers",
      "following_url": "https://api.github.com/users/jdalton/following{/other_user}",
      "gists_url": "https://api.github.com/users/jdalton/gists{/gist_id}",
      "starred_url": "https://api.github.com/users/jdalton/starred{/owner}{/repo}",
      "subscriptions_url": "https://api.github.com/users/jdalton/subscriptions",
      "organizations_url": "https://api.github.com/users/jdalton/orgs",
      "repos_url": "https://api.github.com/users/jdalton/repos",
      "events_url": "https://api.github.com/users/jdalton/events{/privacy}",
      "received_events_url": "https://api.github.com/users/jdalton/received_events",
      "type": "User",
      "site_admin": false
    },
    "created_at": "2015-07-13T14:09:15Z",
    "updated_at": "2015-07-13T14:09:15Z",
    "author_association": "MEMBER",
    "body": "Thanks @iamolivinius! I believe this is resolved in edge.\n",
    "reactions": {
      "url": "https://api.github.com/repos/lodash/lodash/issues/comments/120939755/reactions",
      "total_count": 0,
      "+1": 0,
      "-1": 0,
      "laugh": 0,
      "hooray": 0,
      "confused": 0,
      "heart": 0,
      "rocket": 0,
      "eyes": 0
    },
    "performed_via_github_app": null
  },
  {
    "url": "https://api.github.com/repos/lodash/lodash/issues/comments/120941170",
    "html_url": "https://github.com/lodash/lodash/pull/1340#issuecomment-120941170",
    "issue_url": "https://api.github.com/repos/lodash/lodash/issues/1340",
    "id": 120941170,
    "node_id": "MDEyOklzc3VlQ29tbWVudDEyMDk0MTE3MA==",
    "user": {
      "login": "iamolivinius",
      "id": 832245,
      "node_id": "MDQ6VXNlcjgzMjI0NQ==",
      "avatar_url": "https://avatars.githubusercontent.com/u/832245?v=4",
      "gravatar_id": "",
      "url": "https://api.github.com/users/iamolivinius",
      "html_url": "https://github.com/iamolivinius",
      "followers_url": "https://api.github.com/users/iamolivinius/followers",
      "following_url": "https://api.github.com/users/iamolivinius/following{/other_user}",
      "gists_url": "https://api.github.com/users/iamolivinius/gists{/gist_id}",
      "starred_url": "https://api.github.com/users/iamolivinius/starred{/owner}{/repo}",
      "subscriptions_url": "https://api.github.com/users/iamolivinius/subscriptions",
      "organizations_url": "https://api.github.com/users/iamolivinius/orgs",
      "repos_url": "https://api.github.com/users/iamolivinius/repos",
      "events_url": "https://api.github.com/users/iamolivinius/events{/privacy}",
      "received_events_url": "https://api.github.com/users/iamolivinius/received_events",
      "type": "User",
      "site_admin": false
    },
    "created_at": "2015-07-13T14:12:59Z",
    "updated_at": "2015-07-13T14:12:59Z",
    "author_association": "CONTRIBUTOR",
    "body": "By edge you mean the current master? \n",
    "reactions": {
      "url": "https://api.github.com/repos/lodash/lodash/issues/comments/120941170/reactions",
      "total_count": 0,
      "+1": 0,
      "-1": 0,
      "laugh": 0,
      "hooray": 0,
      "confused": 0,
      "heart": 0,
      "rocket": 0,
      "eyes": 0
    },
    "performed_via_github_app": null
  },
  {
    "url": "https://api.github.com/repos/lodash/lodash/issues/comments/120942481",
    "html_url": "https://github.com/lodash/lodash/pull/1340#issuecomment-120942481",
    "issue_url": "https://api.github.com/repos/lodash/lodash/issues/1340",
    "id": 120942481,
    "node_id": "MDEyOklzc3VlQ29tbWVudDEyMDk0MjQ4MQ==",
    "user": {
      "login": "jdalton",
      "id": 4303,
      "node_id": "MDQ6VXNlcjQzMDM=",
      "avatar_url": "https://avatars.githubusercontent.com/u/4303?v=4",
      "gravatar_id": "",
      "url": "https://api.github.com/users/jdalton",
      "html_url": "https://github.com/jdalton",
      "followers_url": "https://api.github.com/users/jdalton/followers",
      "following_url": "https://api.github.com/users/jdalton/following{/other_user}",
      "gists_url": "https://api.github.com/users/jdalton/gists{/gist_id}",
      "starred_url": "https://api.github.com/users/jdalton/starred{/owner}{/repo}",
      "subscriptions_url": "https://api.github.com/users/jdalton/subscriptions",
      "organizations_url": "https://api.github.com/users/jdalton/orgs",
      "repos_url": "https://api.github.com/users/jdalton/repos",
      "events_url": "https://api.github.com/users/jdalton/events{/privacy}",
      "received_events_url": "https://api.github.com/users/jdalton/received_events",
      "type": "User",
      "site_admin": false
    },
    "created_at": "2015-07-13T14:17:32Z",
    "updated_at": "2015-07-13T14:17:47Z",
    "author_association": "MEMBER",
    "body": "Yep. Give it a try and see if it works.\n",
    "reactions": {
      "url": "https://api.github.com/repos/lodash/lodash/issues/comments/120942481/reactions",
      "total_count": 0,
      "+1": 0,
      "-1": 0,
      "laugh": 0,
      "hooray": 0,
      "confused": 0,
      "heart": 0,
      "rocket": 0,
      "eyes": 0
    },
    "performed_via_github_app": null
  },
  {
    "url": "https://api.github.com/repos/lodash/lodash/issues/comments/120944165",
    "html_url": "https://github.com/lodash/lodash/pull/1340#issuecomment-120944165",
    "issue_url": "https://api.github.com/repos/lodash/lodash/issues/1340",
    "id": 120944165,
    "node_id": "MDEyOklzc3VlQ29tbWVudDEyMDk0NDE2NQ==",
    "user": {
      "login": "iamolivinius",
      "id": 832245,
      "node_id": "MDQ6VXNlcjgzMjI0NQ==",
      "avatar_url": "https://avatars.githubusercontent.com/u/832245?v=4",
      "gravatar_id": "",
      "url": "https://api.github.com/users/iamolivinius",
      "html_url": "https://github.com/iamolivinius",
      "followers_url": "https://api.github.com/users/iamolivinius/followers",
      "following_url": "https://api.github.com/users/iamolivinius/following{/other_user}",
      "gists_url": "https://api.github.com/users/iamolivinius/gists{/gist_id}",
      "starred_url": "https://api.github.com/users/iamolivinius/starred{/owner}{/repo}",
      "subscriptions_url": "https://api.github.com/users/iamolivinius/subscriptions",
      "organizations_url": "https://api.github.com/users/iamolivinius/orgs",
      "repos_url": "https://api.github.com/users/iamolivinius/repos",
      "events_url": "https://api.github.com/users/iamolivinius/events{/privacy}",
      "received_events_url": "https://api.github.com/users/iamolivinius/received_events",
      "type": "User",
      "site_admin": false
    },
    "created_at": "2015-07-13T14:20:52Z",
    "updated_at": "2015-07-13T14:20:52Z",
    "author_association": "CONTRIBUTOR",
    "body": "Tested this file: https://github.com/lodash/lodash/blob/master/lodash.src.js\n\nBug is not resolved.\n",
    "reactions": {
      "url": "https://api.github.com/repos/lodash/lodash/issues/comments/120944165/reactions",
      "total_count": 0,
      "+1": 0,
      "-1": 0,
      "laugh": 0,
      "hooray": 0,
      "confused": 0,
      "heart": 0,
      "rocket": 0,
      "eyes": 0
    },
    "performed_via_github_app": null
  },
  {
    "url": "https://api.github.com/repos/lodash/lodash/issues/comments/120946491",
    "html_url": "https://github.com/lodash/lodash/pull/1340#issuecomment-120946491",
    "issue_url": "https://api.github.com/repos/lodash/lodash/issues/1340",
    "id": 120946491,
    "node_id": "MDEyOklzc3VlQ29tbWVudDEyMDk0NjQ5MQ==",
    "user": {
      "login": "jdalton",
      "id": 4303,
      "node_id": "MDQ6VXNlcjQzMDM=",
      "avatar_url": "https://avatars.githubusercontent.com/u/4303?v=4",
      "gravatar_id": "",
      "url": "https://api.github.com/users/jdalton",
      "html_url": "https://github.com/jdalton",
      "followers_url": "https://api.github.com/users/jdalton/followers",
      "following_url": "https://api.github.com/users/jdalton/following{/other_user}",
      "gists_url": "https://api.github.com/users/jdalton/gists{/gist_id}",
      "starred_url": "https://api.github.com/users/jdalton/starred{/owner}{/repo}",
      "subscriptions_url": "https://api.github.com/users/jdalton/subscriptions",
      "organizations_url": "https://api.github.com/users/jdalton/orgs",
      "repos_url": "https://api.github.com/users/jdalton/repos",
      "events_url": "https://api.github.com/users/jdalton/events{/privacy}",
      "received_events_url": "https://api.github.com/users/jdalton/received_events",
      "type": "User",
      "site_admin": false
    },
    "created_at": "2015-07-13T14:24:03Z",
    "updated_at": "2015-07-13T14:24:03Z",
    "author_association": "MEMBER",
    "body": "Yay! Can you dig a bit to see which branch it ends up taking in the bug case.\n",
    "reactions": {
      "url": "https://api.github.com/repos/lodash/lodash/issues/comments/120946491/reactions",
      "total_count": 0,
      "+1": 0,
      "-1": 0,
      "laugh": 0,
      "hooray": 0,
      "confused": 0,
      "heart": 0,
      "rocket": 0,
      "eyes": 0
    },
    "performed_via_github_app": null
  },
  {
    "url": "https://api.github.com/repos/lodash/lodash/issues/comments/120949440",
    "html_url": "https://github.com/lodash/lodash/pull/1340#issuecomment-120949440",
    "issue_url": "https://api.github.com/repos/lodash/lodash/issues/1340",
    "id": 120949440,
    "node_id": "MDEyOklzc3VlQ29tbWVudDEyMDk0OTQ0MA==",
    "user": {
      "login": "megawac",
      "id": 3475472,
      "node_id": "MDQ6VXNlcjM0NzU0NzI=",
      "avatar_url": "https://avatars.githubusercontent.com/u/3475472?v=4",
      "gravatar_id": "",
      "url": "https://api.github.com/users/megawac",
      "html_url": "https://github.com/megawac",
      "followers_url": "https://api.github.com/users/megawac/followers",
      "following_url": "https://api.github.com/users/megawac/following{/other_user}",
      "gists_url": "https://api.github.com/users/megawac/gists{/gist_id}",
      "starred_url": "https://api.github.com/users/megawac/starred{/owner}{/repo}",
      "subscriptions_url": "https://api.github.com/users/megawac/subscriptions",
      "organizations_url": "https://api.github.com/users/megawac/orgs",
      "repos_url": "https://api.github.com/users/megawac/repos",
      "events_url": "https://api.github.com/users/megawac/events{/privacy}",
      "received_events_url": "https://api.github.com/users/megawac/received_events",
      "type": "User",
      "site_admin": false
    },
    "created_at": "2015-07-13T14:30:12Z",
    "updated_at": "2015-07-13T14:30:47Z",
    "author_association": "CONTRIBUTOR",
    "body": "Want to reopen? @jdalton you can consider using underscores approach which works in FF sandboxs last I checked\n\n``` js\ntypeof self === 'object' && self.self === self && self\n```\n",
    "reactions": {
      "url": "https://api.github.com/repos/lodash/lodash/issues/comments/120949440/reactions",
      "total_count": 0,
      "+1": 0,
      "-1": 0,
      "laugh": 0,
      "hooray": 0,
      "confused": 0,
      "heart": 0,
      "rocket": 0,
      "eyes": 0
    },
    "performed_via_github_app": null
  },
  {
    "url": "https://api.github.com/repos/lodash/lodash/issues/comments/120949784",
    "html_url": "https://github.com/lodash/lodash/pull/1340#issuecomment-120949784",
    "issue_url": "https://api.github.com/repos/lodash/lodash/issues/1340",
    "id": 120949784,
    "node_id": "MDEyOklzc3VlQ29tbWVudDEyMDk0OTc4NA==",
    "user": {
      "login": "iamolivinius",
      "id": 832245,
      "node_id": "MDQ6VXNlcjgzMjI0NQ==",
      "avatar_url": "https://avatars.githubusercontent.com/u/832245?v=4",
      "gravatar_id": "",
      "url": "https://api.github.com/users/iamolivinius",
      "html_url": "https://github.com/iamolivinius",
      "followers_url": "https://api.github.com/users/iamolivinius/followers",
      "following_url": "https://api.github.com/users/iamolivinius/following{/other_user}",
      "gists_url": "https://api.github.com/users/iamolivinius/gists{/gist_id}",
      "starred_url": "https://api.github.com/users/iamolivinius/starred{/owner}{/repo}",
      "subscriptions_url": "https://api.github.com/users/iamolivinius/subscriptions",
      "organizations_url": "https://api.github.com/users/iamolivinius/orgs",
      "repos_url": "https://api.github.com/users/iamolivinius/repos",
      "events_url": "https://api.github.com/users/iamolivinius/events{/privacy}",
      "received_events_url": "https://api.github.com/users/iamolivinius/received_events",
      "type": "User",
      "site_admin": false
    },
    "created_at": "2015-07-13T14:31:45Z",
    "updated_at": "2015-07-13T14:31:45Z",
    "author_association": "CONTRIBUTOR",
    "body": "@megawac Can confirm this. Checked it a week ago.\n",
    "reactions": {
      "url": "https://api.github.com/repos/lodash/lodash/issues/comments/120949784/reactions",
      "total_count": 0,
      "+1": 0,
      "-1": 0,
      "laugh": 0,
      "hooray": 0,
      "confused": 0,
      "heart": 0,
      "rocket": 0,
      "eyes": 0
    },
    "performed_via_github_app": null
  },
  {
    "url": "https://api.github.com/repos/lodash/lodash/issues/comments/120952673",
    "html_url": "https://github.com/lodash/lodash/pull/1340#issuecomment-120952673",
    "issue_url": "https://api.github.com/repos/lodash/lodash/issues/1340",
    "id": 120952673,
    "node_id": "MDEyOklzc3VlQ29tbWVudDEyMDk1MjY3Mw==",
    "user": {
      "login": "iamolivinius",
      "id": 832245,
      "node_id": "MDQ6VXNlcjgzMjI0NQ==",
      "avatar_url": "https://avatars.githubusercontent.com/u/832245?v=4",
      "gravatar_id": "",
      "url": "https://api.github.com/users/iamolivinius",
      "html_url": "https://github.com/iamolivinius",
      "followers_url": "https://api.github.com/users/iamolivinius/followers",
      "following_url": "https://api.github.com/users/iamolivinius/following{/other_user}",
      "gists_url": "https://api.github.com/users/iamolivinius/gists{/gist_id}",
      "starred_url": "https://api.github.com/users/iamolivinius/starred{/owner}{/repo}",
      "subscriptions_url": "https://api.github.com/users/iamolivinius/subscriptions",
      "organizations_url": "https://api.github.com/users/iamolivinius/orgs",
      "repos_url": "https://api.github.com/users/iamolivinius/repos",
      "events_url": "https://api.github.com/users/iamolivinius/events{/privacy}",
      "received_events_url": "https://api.github.com/users/iamolivinius/received_events",
      "type": "User",
      "site_admin": false
    },
    "created_at": "2015-07-13T14:41:10Z",
    "updated_at": "2015-07-13T14:41:10Z",
    "author_association": "CONTRIBUTOR",
    "body": "@jdalton I'd love to help out but I'm not sure if I get it right what you were asking for. (non-native speaker)\n\nYou want me to find out in which branch the bug is present, right?!\n",
    "reactions": {
      "url": "https://api.github.com/repos/lodash/lodash/issues/comments/120952673/reactions",
      "total_count": 0,
      "+1": 0,
      "-1": 0,
      "laugh": 0,
      "hooray": 0,
      "confused": 0,
      "heart": 0,
      "rocket": 0,
      "eyes": 0
    },
    "performed_via_github_app": null
  },
  {
    "url": "https://api.github.com/repos/lodash/lodash/issues/comments/120953139",
    "html_url": "https://github.com/lodash/lodash/pull/1340#issuecomment-120953139",
    "issue_url": "https://api.github.com/repos/lodash/lodash/issues/1340",
    "id": 120953139,
    "node_id": "MDEyOklzc3VlQ29tbWVudDEyMDk1MzEzOQ==",
    "user": {
      "login": "megawac",
      "id": 3475472,
      "node_id": "MDQ6VXNlcjM0NzU0NzI=",
      "avatar_url": "https://avatars.githubusercontent.com/u/3475472?v=4",
      "gravatar_id": "",
      "url": "https://api.github.com/users/megawac",
      "html_url": "https://github.com/megawac",
      "followers_url": "https://api.github.com/users/megawac/followers",
      "following_url": "https://api.github.com/users/megawac/following{/other_user}",
      "gists_url": "https://api.github.com/users/megawac/gists{/gist_id}",
      "starred_url": "https://api.github.com/users/megawac/starred{/owner}{/repo}",
      "subscriptions_url": "https://api.github.com/users/megawac/subscriptions",
      "organizations_url": "https://api.github.com/users/megawac/orgs",
      "repos_url": "https://api.github.com/users/megawac/repos",
      "events_url": "https://api.github.com/users/megawac/events{/privacy}",
      "received_events_url": "https://api.github.com/users/megawac/received_events",
      "type": "User",
      "site_admin": false
    },
    "created_at": "2015-07-13T14:43:08Z",
    "updated_at": "2015-07-13T14:43:45Z",
    "author_association": "CONTRIBUTOR",
    "body": "@iamolivinius can you verify https://github.com/megawac/lodash/commit/46baf7d3848c10ced2f17d8d741fda662a77054c solves your issue?\n\n[Source code](https://github.com/megawac/lodash/blob/46baf7d3848c10ced2f17d8d741fda662a77054c/lodash.src.js)\n",
    "reactions": {
      "url": "https://api.github.com/repos/lodash/lodash/issues/comments/120953139/reactions",
      "total_count": 0,
      "+1": 0,
      "-1": 0,
      "laugh": 0,
      "hooray": 0,
      "confused": 0,
      "heart": 0,
      "rocket": 0,
      "eyes": 0
    },
    "performed_via_github_app": null
  },
  {
    "url": "https://api.github.com/repos/lodash/lodash/issues/comments/120963906",
    "html_url": "https://github.com/lodash/lodash/pull/1340#issuecomment-120963906",
    "issue_url": "https://api.github.com/repos/lodash/lodash/issues/1340",
    "id": 120963906,
    "node_id": "MDEyOklzc3VlQ29tbWVudDEyMDk2MzkwNg==",
    "user": {
      "login": "iamolivinius",
      "id": 832245,
      "node_id": "MDQ6VXNlcjgzMjI0NQ==",
      "avatar_url": "https://avatars.githubusercontent.com/u/832245?v=4",
      "gravatar_id": "",
      "url": "https://api.github.com/users/iamolivinius",
      "html_url": "https://github.com/iamolivinius",
      "followers_url": "https://api.github.com/users/iamolivinius/followers",
      "following_url": "https://api.github.com/users/iamolivinius/following{/other_user}",
      "gists_url": "https://api.github.com/users/iamolivinius/gists{/gist_id}",
      "starred_url": "https://api.github.com/users/iamolivinius/starred{/owner}{/repo}",
      "subscriptions_url": "https://api.github.com/users/iamolivinius/subscriptions",
      "organizations_url": "https://api.github.com/users/iamolivinius/orgs",
      "repos_url": "https://api.github.com/users/iamolivinius/repos",
      "events_url": "https://api.github.com/users/iamolivinius/events{/privacy}",
      "received_events_url": "https://api.github.com/users/iamolivinius/received_events",
      "type": "User",
      "site_admin": false
    },
    "created_at": "2015-07-13T15:16:57Z",
    "updated_at": "2015-07-13T15:16:57Z",
    "author_association": "CONTRIBUTOR",
    "body": "No, it doesn't fix the problem.\n",
    "reactions": {
      "url": "https://api.github.com/repos/lodash/lodash/issues/comments/120963906/reactions",
      "total_count": 0,
      "+1": 0,
      "-1": 0,
      "laugh": 0,
      "hooray": 0,
      "confused": 0,
      "heart": 0,
      "rocket": 0,
      "eyes": 0
    },
    "performed_via_github_app": null
  },
  {
    "url": "https://api.github.com/repos/lodash/lodash/issues/comments/120967439",
    "html_url": "https://github.com/lodash/lodash/pull/1340#issuecomment-120967439",
    "issue_url": "https://api.github.com/repos/lodash/lodash/issues/1340",
    "id": 120967439,
    "node_id": "MDEyOklzc3VlQ29tbWVudDEyMDk2NzQzOQ==",
    "user": {
      "login": "iamolivinius",
      "id": 832245,
      "node_id": "MDQ6VXNlcjgzMjI0NQ==",
      "avatar_url": "https://avatars.githubusercontent.com/u/832245?v=4",
      "gravatar_id": "",
      "url": "https://api.github.com/users/iamolivinius",
      "html_url": "https://github.com/iamolivinius",
      "followers_url": "https://api.github.com/users/iamolivinius/followers",
      "following_url": "https://api.github.com/users/iamolivinius/following{/other_user}",
      "gists_url": "https://api.github.com/users/iamolivinius/gists{/gist_id}",
      "starred_url": "https://api.github.com/users/iamolivinius/starred{/owner}{/repo}",
      "subscriptions_url": "https://api.github.com/users/iamolivinius/subscriptions",
      "organizations_url": "https://api.github.com/users/iamolivinius/orgs",
      "repos_url": "https://api.github.com/users/iamolivinius/repos",
      "events_url": "https://api.github.com/users/iamolivinius/events{/privacy}",
      "received_events_url": "https://api.github.com/users/iamolivinius/received_events",
      "type": "User",
      "site_admin": false
    },
    "created_at": "2015-07-13T15:26:24Z",
    "updated_at": "2015-07-13T15:26:24Z",
    "author_association": "CONTRIBUTOR",
    "body": "`window` as well as `self` will return a function in `checkGlobal(value){ value.Object }`\n",
    "reactions": {
      "url": "https://api.github.com/repos/lodash/lodash/issues/comments/120967439/reactions",
      "total_count": 0,
      "+1": 0,
      "-1": 0,
      "laugh": 0,
      "hooray": 0,
      "confused": 0,
      "heart": 0,
      "rocket": 0,
      "eyes": 0
    },
    "performed_via_github_app": null
  },
  {
    "url": "https://api.github.com/repos/lodash/lodash/issues/comments/120992264",
    "html_url": "https://github.com/lodash/lodash/pull/1340#issuecomment-120992264",
    "issue_url": "https://api.github.com/repos/lodash/lodash/issues/1340",
    "id": 120992264,
    "node_id": "MDEyOklzc3VlQ29tbWVudDEyMDk5MjI2NA==",
    "user": {
      "login": "jdalton",
      "id": 4303,
      "node_id": "MDQ6VXNlcjQzMDM=",
      "avatar_url": "https://avatars.githubusercontent.com/u/4303?v=4",
      "gravatar_id": "",
      "url": "https://api.github.com/users/jdalton",
      "html_url": "https://github.com/jdalton",
      "followers_url": "https://api.github.com/users/jdalton/followers",
      "following_url": "https://api.github.com/users/jdalton/following{/other_user}",
      "gists_url": "https://api.github.com/users/jdalton/gists{/gist_id}",
      "starred_url": "https://api.github.com/users/jdalton/starred{/owner}{/repo}",
      "subscriptions_url": "https://api.github.com/users/jdalton/subscriptions",
      "organizations_url": "https://api.github.com/users/jdalton/orgs",
      "repos_url": "https://api.github.com/users/jdalton/repos",
      "events_url": "https://api.github.com/users/jdalton/events{/privacy}",
      "received_events_url": "https://api.github.com/users/jdalton/received_events",
      "type": "User",
      "site_admin": false
    },
    "created_at": "2015-07-13T16:54:41Z",
    "updated_at": "2015-07-13T16:54:41Z",
    "author_association": "MEMBER",
    "body": "How about simply changing `checkGlobal` to:\n\n``` js\nfunction checkGlobal(value) {\n  return (value && value.Object === Object) ? value : null;\n}\n```\n",
    "reactions": {
      "url": "https://api.github.com/repos/lodash/lodash/issues/comments/120992264/reactions",
      "total_count": 0,
      "+1": 0,
      "-1": 0,
      "laugh": 0,
      "hooray": 0,
      "confused": 0,
      "heart": 0,
      "rocket": 0,
      "eyes": 0
    },
    "performed_via_github_app": null
  },
  {
    "url": "https://api.github.com/repos/lodash/lodash/issues/comments/120995753",
    "html_url": "https://github.com/lodash/lodash/pull/1340#issuecomment-120995753",
    "issue_url": "https://api.github.com/repos/lodash/lodash/issues/1340",
    "id": 120995753,
    "node_id": "MDEyOklzc3VlQ29tbWVudDEyMDk5NTc1Mw==",
    "user": {
      "login": "iamolivinius",
      "id": 832245,
      "node_id": "MDQ6VXNlcjgzMjI0NQ==",
      "avatar_url": "https://avatars.githubusercontent.com/u/832245?v=4",
      "gravatar_id": "",
      "url": "https://api.github.com/users/iamolivinius",
      "html_url": "https://github.com/iamolivinius",
      "followers_url": "https://api.github.com/users/iamolivinius/followers",
      "following_url": "https://api.github.com/users/iamolivinius/following{/other_user}",
      "gists_url": "https://api.github.com/users/iamolivinius/gists{/gist_id}",
      "starred_url": "https://api.github.com/users/iamolivinius/starred{/owner}{/repo}",
      "subscriptions_url": "https://api.github.com/users/iamolivinius/subscriptions",
      "organizations_url": "https://api.github.com/users/iamolivinius/orgs",
      "repos_url": "https://api.github.com/users/iamolivinius/repos",
      "events_url": "https://api.github.com/users/iamolivinius/events{/privacy}",
      "received_events_url": "https://api.github.com/users/iamolivinius/received_events",
      "type": "User",
      "site_admin": false
    },
    "created_at": "2015-07-13T17:11:15Z",
    "updated_at": "2015-07-13T17:11:15Z",
    "author_association": "CONTRIBUTOR",
    "body": "In this case `freeGlobal || freeWindow || freeSelf || thisGlobal` would be `null` if you use things like `browserify --bare` cause of the encapsulating self invoking function.\n\nHow about your suggested `checkGlobal` and this: \n\n``` js\nvar root = freeGlobal || freeWindow || freeSelf || thisGlobal || Function('return this')()\n```\n",
    "reactions": {
      "url": "https://api.github.com/repos/lodash/lodash/issues/comments/120995753/reactions",
      "total_count": 0,
      "+1": 0,
      "-1": 0,
      "laugh": 0,
      "hooray": 0,
      "confused": 0,
      "heart": 0,
      "rocket": 0,
      "eyes": 0
    },
    "performed_via_github_app": null
  },
  {
    "url": "https://api.github.com/repos/lodash/lodash/issues/comments/120997318",
    "html_url": "https://github.com/lodash/lodash/pull/1340#issuecomment-120997318",
    "issue_url": "https://api.github.com/repos/lodash/lodash/issues/1340",
    "id": 120997318,
    "node_id": "MDEyOklzc3VlQ29tbWVudDEyMDk5NzMxOA==",
    "user": {
      "login": "jdalton",
      "id": 4303,
      "node_id": "MDQ6VXNlcjQzMDM=",
      "avatar_url": "https://avatars.githubusercontent.com/u/4303?v=4",
      "gravatar_id": "",
      "url": "https://api.github.com/users/jdalton",
      "html_url": "https://github.com/jdalton",
      "followers_url": "https://api.github.com/users/jdalton/followers",
      "following_url": "https://api.github.com/users/jdalton/following{/other_user}",
      "gists_url": "https://api.github.com/users/jdalton/gists{/gist_id}",
      "starred_url": "https://api.github.com/users/jdalton/starred{/owner}{/repo}",
      "subscriptions_url": "https://api.github.com/users/jdalton/subscriptions",
      "organizations_url": "https://api.github.com/users/jdalton/orgs",
      "repos_url": "https://api.github.com/users/jdalton/repos",
      "events_url": "https://api.github.com/users/jdalton/events{/privacy}",
      "received_events_url": "https://api.github.com/users/jdalton/received_events",
      "type": "User",
      "site_admin": false
    },
    "created_at": "2015-07-13T17:18:52Z",
    "updated_at": "2015-07-13T17:19:46Z",
    "author_association": "MEMBER",
    "body": "I think the Hail Mary at the end is fine. It won't likely hit so the issues with CSP enviros should be minimum.\n\nFeel free to make the modifications. Have you signed [our CLA](http://dojofoundation.org/about/claForm)?\n",
    "reactions": {
      "url": "https://api.github.com/repos/lodash/lodash/issues/comments/120997318/reactions",
      "total_count": 0,
      "+1": 0,
      "-1": 0,
      "laugh": 0,
      "hooray": 0,
      "confused": 0,
      "heart": 0,
      "rocket": 0,
      "eyes": 0
    },
    "performed_via_github_app": null
  },
  {
    "url": "https://api.github.com/repos/lodash/lodash/issues/comments/121004582",
    "html_url": "https://github.com/lodash/lodash/pull/1340#issuecomment-121004582",
    "issue_url": "https://api.github.com/repos/lodash/lodash/issues/1340",
    "id": 121004582,
    "node_id": "MDEyOklzc3VlQ29tbWVudDEyMTAwNDU4Mg==",
    "user": {
      "login": "iamolivinius",
      "id": 832245,
      "node_id": "MDQ6VXNlcjgzMjI0NQ==",
      "avatar_url": "https://avatars.githubusercontent.com/u/832245?v=4",
      "gravatar_id": "",
      "url": "https://api.github.com/users/iamolivinius",
      "html_url": "https://github.com/iamolivinius",
      "followers_url": "https://api.github.com/users/iamolivinius/followers",
      "following_url": "https://api.github.com/users/iamolivinius/following{/other_user}",
      "gists_url": "https://api.github.com/users/iamolivinius/gists{/gist_id}",
      "starred_url": "https://api.github.com/users/iamolivinius/starred{/owner}{/repo}",
      "subscriptions_url": "https://api.github.com/users/iamolivinius/subscriptions",
      "organizations_url": "https://api.github.com/users/iamolivinius/orgs",
      "repos_url": "https://api.github.com/users/iamolivinius/repos",
      "events_url": "https://api.github.com/users/iamolivinius/events{/privacy}",
      "received_events_url": "https://api.github.com/users/iamolivinius/received_events",
      "type": "User",
      "site_admin": false
    },
    "created_at": "2015-07-13T17:50:29Z",
    "updated_at": "2015-07-13T18:32:33Z",
    "author_association": "CONTRIBUTOR",
    "body": "I signed the CLA a few minutes ago (submitted on 2015-07-13 17:27:23)\n",
    "reactions": {
      "url": "https://api.github.com/repos/lodash/lodash/issues/comments/121004582/reactions",
      "total_count": 0,
      "+1": 0,
      "-1": 0,
      "laugh": 0,
      "hooray": 0,
      "confused": 0,
      "heart": 0,
      "rocket": 0,
      "eyes": 0
    },
    "performed_via_github_app": null
  },
  {
    "url": "https://api.github.com/repos/lodash/lodash/issues/comments/121007480",
    "html_url": "https://github.com/lodash/lodash/pull/1340#issuecomment-121007480",
    "issue_url": "https://api.github.com/repos/lodash/lodash/issues/1340",
    "id": 121007480,
    "node_id": "MDEyOklzc3VlQ29tbWVudDEyMTAwNzQ4MA==",
    "user": {
      "login": "jridgewell",
      "id": 112982,
      "node_id": "MDQ6VXNlcjExMjk4Mg==",
      "avatar_url": "https://avatars.githubusercontent.com/u/112982?v=4",
      "gravatar_id": "",
      "url": "https://api.github.com/users/jridgewell",
      "html_url": "https://github.com/jridgewell",
      "followers_url": "https://api.github.com/users/jridgewell/followers",
      "following_url": "https://api.github.com/users/jridgewell/following{/other_user}",
      "gists_url": "https://api.github.com/users/jridgewell/gists{/gist_id}",
      "starred_url": "https://api.github.com/users/jridgewell/starred{/owner}{/repo}",
      "subscriptions_url": "https://api.github.com/users/jridgewell/subscriptions",
      "organizations_url": "https://api.github.com/users/jridgewell/orgs",
      "repos_url": "https://api.github.com/users/jridgewell/repos",
      "events_url": "https://api.github.com/users/jridgewell/events{/privacy}",
      "received_events_url": "https://api.github.com/users/jridgewell/received_events",
      "type": "User",
      "site_admin": false
    },
    "created_at": "2015-07-13T18:00:14Z",
    "updated_at": "2015-07-13T18:00:14Z",
    "author_association": "CONTRIBUTOR",
    "body": "CSP isn't done by static analysis?\n",
    "reactions": {
      "url": "https://api.github.com/repos/lodash/lodash/issues/comments/121007480/reactions",
      "total_count": 0,
      "+1": 0,
      "-1": 0,
      "laugh": 0,
      "hooray": 0,
      "confused": 0,
      "heart": 0,
      "rocket": 0,
      "eyes": 0
    },
    "performed_via_github_app": null
  },
  {
    "url": "https://api.github.com/repos/lodash/lodash/issues/comments/121011362",
    "html_url": "https://github.com/lodash/lodash/pull/1340#issuecomment-121011362",
    "issue_url": "https://api.github.com/repos/lodash/lodash/issues/1340",
    "id": 121011362,
    "node_id": "MDEyOklzc3VlQ29tbWVudDEyMTAxMTM2Mg==",
    "user": {
      "login": "iamolivinius",
      "id": 832245,
      "node_id": "MDQ6VXNlcjgzMjI0NQ==",
      "avatar_url": "https://avatars.githubusercontent.com/u/832245?v=4",
      "gravatar_id": "",
      "url": "https://api.github.com/users/iamolivinius",
      "html_url": "https://github.com/iamolivinius",
      "followers_url": "https://api.github.com/users/iamolivinius/followers",
      "following_url": "https://api.github.com/users/iamolivinius/following{/other_user}",
      "gists_url": "https://api.github.com/users/iamolivinius/gists{/gist_id}",
      "starred_url": "https://api.github.com/users/iamolivinius/starred{/owner}{/repo}",
      "subscriptions_url": "https://api.github.com/users/iamolivinius/subscriptions",
      "organizations_url": "https://api.github.com/users/iamolivinius/orgs",
      "repos_url": "https://api.github.com/users/iamolivinius/repos",
      "events_url": "https://api.github.com/users/iamolivinius/events{/privacy}",
      "received_events_url": "https://api.github.com/users/iamolivinius/received_events",
      "type": "User",
      "site_admin": false
    },
    "created_at": "2015-07-13T18:15:11Z",
    "updated_at": "2015-07-13T18:15:11Z",
    "author_association": "CONTRIBUTOR",
    "body": "Are you referring to `Function('return this')()`?\n",
    "reactions": {
      "url": "https://api.github.com/repos/lodash/lodash/issues/comments/121011362/reactions",
      "total_count": 0,
      "+1": 0,
      "-1": 0,
      "laugh": 0,
      "hooray": 0,
      "confused": 0,
      "heart": 0,
      "rocket": 0,
      "eyes": 0
    },
    "performed_via_github_app": null
  },
  {
    "url": "https://api.github.com/repos/lodash/lodash/issues/comments/121016603",
    "html_url": "https://github.com/lodash/lodash/pull/1340#issuecomment-121016603",
    "issue_url": "https://api.github.com/repos/lodash/lodash/issues/1340",
    "id": 121016603,
    "node_id": "MDEyOklzc3VlQ29tbWVudDEyMTAxNjYwMw==",
    "user": {
      "login": "jdalton",
      "id": 4303,
      "node_id": "MDQ6VXNlcjQzMDM=",
      "avatar_url": "https://avatars.githubusercontent.com/u/4303?v=4",
      "gravatar_id": "",
      "url": "https://api.github.com/users/jdalton",
      "html_url": "https://github.com/jdalton",
      "followers_url": "https://api.github.com/users/jdalton/followers",
      "following_url": "https://api.github.com/users/jdalton/following{/other_user}",
      "gists_url": "https://api.github.com/users/jdalton/gists{/gist_id}",
      "starred_url": "https://api.github.com/users/jdalton/starred{/owner}{/repo}",
      "subscriptions_url": "https://api.github.com/users/jdalton/subscriptions",
      "organizations_url": "https://api.github.com/users/jdalton/orgs",
      "repos_url": "https://api.github.com/users/jdalton/repos",
      "events_url": "https://api.github.com/users/jdalton/events{/privacy}",
      "received_events_url": "https://api.github.com/users/jdalton/received_events",
      "type": "User",
      "site_admin": false
    },
    "created_at": "2015-07-13T18:31:43Z",
    "updated_at": "2015-07-13T18:31:43Z",
    "author_association": "MEMBER",
    "body": "@jridgewell\n\n> CSP isn't done by static analysis?\n\nNope.\n\n@iamolivinius\n\n> I signed the CLA a few minutes ago.\n\nRock!\n",
    "reactions": {
      "url": "https://api.github.com/repos/lodash/lodash/issues/comments/121016603/reactions",
      "total_count": 0,
      "+1": 0,
      "-1": 0,
      "laugh": 0,
      "hooray": 0,
      "confused": 0,
      "heart": 0,
      "rocket": 0,
      "eyes": 0
    },
    "performed_via_github_app": null
  },
  {
    "url": "https://api.github.com/repos/lodash/lodash/issues/comments/131660794",
    "html_url": "https://github.com/lodash/lodash/pull/1340#issuecomment-131660794",
    "issue_url": "https://api.github.com/repos/lodash/lodash/issues/1340",
    "id": 131660794,
    "node_id": "MDEyOklzc3VlQ29tbWVudDEzMTY2MDc5NA==",
    "user": {
      "login": "indieisaconcept",
      "id": 640613,
      "node_id": "MDQ6VXNlcjY0MDYxMw==",
      "avatar_url": "https://avatars.githubusercontent.com/u/640613?v=4",
      "gravatar_id": "",
      "url": "https://api.github.com/users/indieisaconcept",
      "html_url": "https://github.com/indieisaconcept",
      "followers_url": "https://api.github.com/users/indieisaconcept/followers",
      "following_url": "https://api.github.com/users/indieisaconcept/following{/other_user}",
      "gists_url": "https://api.github.com/users/indieisaconcept/gists{/gist_id}",
      "starred_url": "https://api.github.com/users/indieisaconcept/starred{/owner}{/repo}",
      "subscriptions_url": "https://api.github.com/users/indieisaconcept/subscriptions",
      "organizations_url": "https://api.github.com/users/indieisaconcept/orgs",
      "repos_url": "https://api.github.com/users/indieisaconcept/repos",
      "events_url": "https://api.github.com/users/indieisaconcept/events{/privacy}",
      "received_events_url": "https://api.github.com/users/indieisaconcept/received_events",
      "type": "User",
      "site_admin": false
    },
    "created_at": "2015-08-17T02:37:58Z",
    "updated_at": "2015-08-17T02:37:58Z",
    "author_association": "NONE",
    "body": "Has this fix made it to npm yet? This solves an issue I have been having using a browserified version of lodash within node-vm.\n\nThe latest version \"3.10.1\" has this change omitted.\n",
    "reactions": {
      "url": "https://api.github.com/repos/lodash/lodash/issues/comments/131660794/reactions",
      "total_count": 0,
      "+1": 0,
      "-1": 0,
      "laugh": 0,
      "hooray": 0,
      "confused": 0,
      "heart": 0,
      "rocket": 0,
      "eyes": 0
    },
    "performed_via_github_app": null
  },
  {
    "url": "https://api.github.com/repos/lodash/lodash/issues/comments/131671817",
    "html_url": "https://github.com/lodash/lodash/pull/1340#issuecomment-131671817",
    "issue_url": "https://api.github.com/repos/lodash/lodash/issues/1340",
    "id": 131671817,
    "node_id": "MDEyOklzc3VlQ29tbWVudDEzMTY3MTgxNw==",
    "user": {
      "login": "jdalton",
      "id": 4303,
      "node_id": "MDQ6VXNlcjQzMDM=",
      "avatar_url": "https://avatars.githubusercontent.com/u/4303?v=4",
      "gravatar_id": "",
      "url": "https://api.github.com/users/jdalton",
      "html_url": "https://github.com/jdalton",
      "followers_url": "https://api.github.com/users/jdalton/followers",
      "following_url": "https://api.github.com/users/jdalton/following{/other_user}",
      "gists_url": "https://api.github.com/users/jdalton/gists{/gist_id}",
      "starred_url": "https://api.github.com/users/jdalton/starred{/owner}{/repo}",
      "subscriptions_url": "https://api.github.com/users/jdalton/subscriptions",
      "organizations_url": "https://api.github.com/users/jdalton/orgs",
      "repos_url": "https://api.github.com/users/jdalton/repos",
      "events_url": "https://api.github.com/users/jdalton/events{/privacy}",
      "received_events_url": "https://api.github.com/users/jdalton/received_events",
      "type": "User",
      "site_admin": false
    },
    "created_at": "2015-08-17T03:42:40Z",
    "updated_at": "2015-08-17T03:42:40Z",
    "author_association": "MEMBER",
    "body": "This will make it in to v4.0.\n",
    "reactions": {
      "url": "https://api.github.com/repos/lodash/lodash/issues/comments/131671817/reactions",
      "total_count": 0,
      "+1": 0,
      "-1": 0,
      "laugh": 0,
      "hooray": 0,
      "confused": 0,
      "heart": 0,
      "rocket": 0,
      "eyes": 0
    },
    "performed_via_github_app": null
  },
  {
    "url": "https://api.github.com/repos/lodash/lodash/issues/comments/131672047",
    "html_url": "https://github.com/lodash/lodash/pull/1340#issuecomment-131672047",
    "issue_url": "https://api.github.com/repos/lodash/lodash/issues/1340",
    "id": 131672047,
    "node_id": "MDEyOklzc3VlQ29tbWVudDEzMTY3MjA0Nw==",
    "user": {
      "login": "indieisaconcept",
      "id": 640613,
      "node_id": "MDQ6VXNlcjY0MDYxMw==",
      "avatar_url": "https://avatars.githubusercontent.com/u/640613?v=4",
      "gravatar_id": "",
      "url": "https://api.github.com/users/indieisaconcept",
      "html_url": "https://github.com/indieisaconcept",
      "followers_url": "https://api.github.com/users/indieisaconcept/followers",
      "following_url": "https://api.github.com/users/indieisaconcept/following{/other_user}",
      "gists_url": "https://api.github.com/users/indieisaconcept/gists{/gist_id}",
      "starred_url": "https://api.github.com/users/indieisaconcept/starred{/owner}{/repo}",
      "subscriptions_url": "https://api.github.com/users/indieisaconcept/subscriptions",
      "organizations_url": "https://api.github.com/users/indieisaconcept/orgs",
      "repos_url": "https://api.github.com/users/indieisaconcept/repos",
      "events_url": "https://api.github.com/users/indieisaconcept/events{/privacy}",
      "received_events_url": "https://api.github.com/users/indieisaconcept/received_events",
      "type": "User",
      "site_admin": false
    },
    "created_at": "2015-08-17T03:46:18Z",
    "updated_at": "2015-08-17T03:46:18Z",
    "author_association": "NONE",
    "body": "@jdalton thanks - I'm pulling from master in the interim.\n",
    "reactions": {
      "url": "https://api.github.com/repos/lodash/lodash/issues/comments/131672047/reactions",
      "total_count": 0,
      "+1": 0,
      "-1": 0,
      "laugh": 0,
      "hooray": 0,
      "confused": 0,
      "heart": 0,
      "rocket": 0,
      "eyes": 0
    },
    "performed_via_github_app": null
  },
  {
    "url": "https://api.github.com/repos/lodash/lodash/issues/comments/450155065",
    "html_url": "https://github.com/lodash/lodash/pull/1340#issuecomment-450155065",
    "issue_url": "https://api.github.com/repos/lodash/lodash/issues/1340",
    "id": 450155065,
    "node_id": "MDEyOklzc3VlQ29tbWVudDQ1MDE1NTA2NQ==",
    "user": {
      "login": "lock[bot]",
      "id": 33595554,
      "node_id": "MDM6Qm90MzM1OTU1NTQ=",
      "avatar_url": "https://avatars.githubusercontent.com/in/6672?v=4",
      "gravatar_id": "",
      "url": "https://api.github.com/users/lock%5Bbot%5D",
      "html_url": "https://github.com/apps/lock",
      "followers_url": "https://api.github.com/users/lock%5Bbot%5D/followers",
      "following_url": "https://api.github.com/users/lock%5Bbot%5D/following{/other_user}",
      "gists_url": "https://api.github.com/users/lock%5Bbot%5D/gists{/gist_id}",
      "starred_url": "https://api.github.com/users/lock%5Bbot%5D/starred{/owner}{/repo}",
      "subscriptions_url": "https://api.github.com/users/lock%5Bbot%5D/subscriptions",
      "organizations_url": "https://api.github.com/users/lock%5Bbot%5D/orgs",
      "repos_url": "https://api.github.com/users/lock%5Bbot%5D/repos",
      "events_url": "https://api.github.com/users/lock%5Bbot%5D/events{/privacy}",
      "received_events_url": "https://api.github.com/users/lock%5Bbot%5D/received_events",
      "type": "Bot",
      "site_admin": false
    },
    "created_at": "2018-12-27T13:56:31Z",
    "updated_at": "2018-12-27T13:56:31Z",
    "author_association": "NONE",
    "body": "This thread has been automatically locked since there has not been any recent activity after it was closed. Please open a new issue for related bugs.\n",
    "reactions": {
      "url": "https://api.github.com/repos/lodash/lodash/issues/comments/450155065/reactions",
      "total_count": 0,
      "+1": 0,
      "-1": 0,
      "laugh": 0,
      "hooray": 0,
      "confused": 0,
      "heart": 0,
      "rocket": 0,
      "eyes": 0
    },
    "performed_via_github_app": null
  }
]